experimenthq/__init__.py
experimenthq/_about.py
experimenthq/experiment.py
experimenthq/notion_types.py
experimenthq-0.2.1.dist-info/LICENSE
experimenthq-0.2.1.dist-info/METADATA
experimenthq-0.2.1.dist-info/WHEEL
experimenthq-0.2.1.dist-info/top_level.txt
experimenthq-0.2.1.dist-info/RECORD
